nigredo_config/__init__.py
nigredo_config/loader.py
nigredo_config_loader-0.2.3.dist-info/licenses/LICENSE
nigredo_config_loader-0.2.3.dist-info/METADATA
nigredo_config_loader-0.2.3.dist-info/WHEEL
nigredo_config_loader-0.2.3.dist-info/top_level.txt
nigredo_config_loader-0.2.3.dist-info/RECORD
